{
  "system": "rag_autoencoder128_k3",
  "sample_count": 10000,
  "accuracy": 0.8855,
  "macro_precision": 0.8861892229053776,
  "macro_recall": 0.8855000000000001,
  "macro_f1": 0.8856036588287275,
  "per_class": [
    {
      "label_id": 0,
      "label_name": "T-shirt/top",
      "precision": 0.8209393346379648,
      "recall": 0.839,
      "f1": 0.8298714144411474,
      "support": 1000
    },
    {
      "label_id": 1,
      "label_name": "Trouser",
      "precision": 0.9918946301925026,
      "recall": 0.979,
      "f1": 0.9854051333668847,
      "support": 1000
    },
    {
      "label_id": 2,
      "label_name": "Pullover",
      "precision": 0.7871720116618076,
      "recall": 0.81,
      "f1": 0.7984228684080829,
      "support": 1000
    },
    {
      "label_id": 3,
      "label_name": "Dress",
      "precision": 0.9055837563451776,
      "recall": 0.892,
      "f1": 0.8987405541561713,
      "support": 1000
    },
    {
      "label_id": 4,
      "label_name": "Coat",
      "precision": 0.7980295566502463,
      "recall": 0.81,
      "f1": 0.8039702233250621,
      "support": 1000
    },
    {
      "label_id": 5,
      "label_name": "Sandal",
      "precision": 0.9946294307196563,
      "recall": 0.926,
      "f1": 0.9590885551527706,
      "support": 1000
    },
    {
      "label_id": 6,
      "label_name": "Shirt",
      "precision": 0.7003089598352215,
      "recall": 0.68,
      "f1": 0.6900050735667174,
      "support": 1000
    },
    {
      "label_id": 7,
      "label_name": "Sneaker",
      "precision": 0.937137330754352,
      "recall": 0.969,
      "f1": 0.9528023598820059,
      "support": 1000
    },
    {
      "label_id": 8,
      "label_name": "Bag",
      "precision": 0.9878542510121457,
      "recall": 0.976,
      "f1": 0.9818913480885312,
      "support": 1000
    },
    {
      "label_id": 9,
      "label_name": "Ankle boot",
      "precision": 0.9383429672447013,
      "recall": 0.974,
      "f1": 0.9558390578999019,
      "support": 1000
    }
  ],
  "confusion_matrix": [
    [
      839,
      0,
      18,
      21,
      6,
      1,
      111,
      0,
      4,
      0
    ],
    [
      4,
      979,
      1,
      10,
      3,
      0,
      2,
      0,
      1,
      0
    ],
    [
      17,
      2,
      810,
      10,
      90,
      0,
      71,
      0,
      0,
      0
    ],
    [
      27,
      4,
      15,
      892,
      32,
      0,
      29,
      0,
      1,
      0
    ],
    [
      1,
      1,
      89,
      28,
      810,
      0,
      70,
      0,
      1,
      0
    ],
    [
      0,
      0,
      0,
      0,
      0,
      926,
      0,
      38,
      0,
      36
    ],
    [
      131,
      1,
      92,
      22,
      69,
      0,
      680,
      0,
      5,
      0
    ],
    [
      0,
      0,
      0,
      0,
      0,
      3,
      0,
      969,
      0,
      28
    ],
    [
      2,
      0,
      4,
      2,
      5,
      0,
      8,
      3,
      976,
      0
    ],
    [
      1,
      0,
      0,
      0,
      0,
      1,
      0,
      24,
      0,
      974
    ]
  ],
  "latency_ms": {
    "average": 117.35104695199989,
    "p50": 90.72875000128988,
    "p95": 280.1404961457592
  },
  "top_k": 3
}